{"stats":{"minecraft:dropped":{"minecraft:totem_of_undying":1,"minecraft:netherite_pickaxe":3,"minecraft:netherite_shovel":2,"minecraft:oak_planks":64,"minecraft:bow":3,"minecraft:wind_charge":15,"minecraft:bucket":1,"minecraft:black_dye":63,"minecraft:iron_ingot":15,"minecraft:splash_potion":15,"minecraft:ender_pearl":37,"minecraft:trident":6,"minecraft:black_banner":1,"minecraft:shield":2,"minecraft:crossbow":6,"spear:netherite_spear":4,"minecraft:mace":6,"minecraft:nether_star":4,"minecraft:netherite_sword":5,"tooltrims:linear_tool_trim_smithing_template":8,"minecraft:string":4,"minecraft:shulker_box":1,"minecraft:netherite_axe":4,"minecraft:writable_book":1,"minecraft:elytra":5,"minecraft:enchanted_golden_apple":48,"minecraft:netherite_hoe":1},"minecraft:mined":{"minecraft:brown_shulker_box":1,"minecraft:black_shulker_box":7,"minecraft:light_gray_shulker_box":1,"minecraft:light_blue_shulker_box":1,"minecraft:tripwire":1,"minecraft:blue_shulker_box":1,"minecraft:purple_shulker_box":1,"minecraft:cobweb":7,"minecraft:green_shulker_box":1,"minecraft:white_shulker_box":1,"minecraft:yellow_shulker_box":1},"minecraft:killed_by":{"minecraft:player":3},"minecraft:used":{"minecraft:orange_shulker_box":2,"minecraft:grass_block":27,"minecraft:netherite_helmet":1,"minecraft:string":1,"minecraft:loom":1,"minecraft:yellow_shulker_box":1,"minecraft:trident":11,"minecraft:shield":6,"minecraft:netherite_sword":85,"minecraft:white_banner":2,"minecraft:green_shulker_box":3,"minecraft:shulker_box":39,"minecraft:firework_rocket":167,"minecraft:golden_carrot":4,"minecraft:milk_bucket":1,"minecraft:red_shulker_box":5,"minecraft:elytra":158,"minecraft:writable_book":1,"minecraft:experience_bottle":145,"minecraft:magenta_shulker_box":3,"minecraft:netherite_boots":1,"minecraft:white_shulker_box":2,"minecraft:netherite_leggings":1,"minecraft:anvil":4,"minecraft:light_gray_shulker_box":28,"minecraft:netherite_pickaxe":15,"minecraft:crossbow":46,"minecraft:purple_shulker_box":1,"minecraft:smooth_stone":1,"minecraft:wind_charge":204,"minecraft:cyan_shulker_box":1,"minecraft:oak_leaves":1,"minecraft:cobweb":24,"minecraft:smithing_table":2,"minecraft:blue_shulker_box":1,"minecraft:mace":82,"minecraft:golden_apple":68,"minecraft:ender_chest":6,"minecraft:crafting_table":2,"minecraft:splash_potion":19,"minecraft:netherite_chestplate":158,"minecraft:totem_of_undying":8,"minecraft:lime_shulker_box":6,"minecraft:ender_pearl":28,"minecraft:bow":29,"minecraft:brown_shulker_box":1,"minecraft:black_shulker_box":18},"minecraft:killed":{"minecraft:iron_golem":23,"minecraft:pig":1,"minecraft:cow":1,"minecraft:villager":2,"minecraft:player":10},"minecraft:custom":{"minecraft:time_since_rest":7122,"minecraft:leave_game":9,"minecraft:damage_taken":9400,"minecraft:mob_kills":28,"minecraft:damage_absorbed":1679,"minecraft:open_shulker_box":500,"minecraft:time_since_death":7095,"minecraft:aviate_one_cm":789531,"minecraft:damage_dealt_absorbed":81,"minecraft:open_enderchest":181,"minecraft:interact_with_smithing_table":53,"minecraft:total_world_time":297597,"minecraft:crouch_one_cm":6057,"minecraft:deaths":4,"minecraft:climb_one_cm":91,"minecraft:player_kills":12,"minecraft:interact_with_loom":7,"minecraft:damage_blocked_by_shield":160,"minecraft:interact_with_crafting_table":4,"minecraft:walk_one_cm":544619,"minecraft:walk_under_water_one_cm":2933,"minecraft:play_time":297597,"minecraft:damage_dealt":23651,"minecraft:jump":1658,"minecraft:drop":86,"minecraft:sprint_one_cm":104817,"minecraft:fall_one_cm":316747,"minecraft:fly_one_cm":934667,"minecraft:interact_with_anvil":108,"minecraft:walk_on_water_one_cm":73,"minecraft:sneak_time":5017},"minecraft:crafted":{"minecraft:mace":5,"minecraft:trident":7,"minecraft:wind_charge":512,"minecraft:red_shulker_box":1,"minecraft:netherite_chestplate":1,"minecraft:netherite_sword":3,"minecraft:shield":4,"minecraft:crossbow":3,"minecraft:netherite_axe":2,"minecraft:lime_shulker_box":1,"minecraft:netherite_pickaxe":3,"minecraft:bow":3,"minecraft:air":0},"minecraft:picked_up":{"minecraft:light_blue_shulker_box":1,"minecraft:trident":2,"minecraft:black_dye":63,"minecraft:lime_shulker_box":5,"minecraft:leather":1,"minecraft:netherite_boots":2,"minecraft:red_shulker_box":3,"minecraft:wooden_axe":1,"minecraft:netherite_pickaxe":1,"minecraft:splash_potion":6,"minecraft:white_shulker_box":4,"minecraft:tipped_arrow":1,"minecraft:light_gray_shulker_box":28,"minecraft:armor_stand":2,"minecraft:black_banner":2,"minecraft:netherite_shovel":1,"minecraft:black_shulker_box":24,"minecraft:totem_of_undying":2,"spear:netherite_spear":2,"minecraft:poppy":3,"minecraft:yellow_shulker_box":2,"minecraft:nether_star":5,"minecraft:netherite_chestplate":2,"minecraft:bow":2,"minecraft:orange_shulker_box":3,"minecraft:iron_ingot":15,"tooltrims:frost_tool_trim_smithing_template":1,"minecraft:brown_shulker_box":2,"minecraft:shulker_box":39,"minecraft:crossbow":2,"minecraft:string":11,"tooltrims:linear_tool_trim_smithing_template":4,"minecraft:writable_book":1,"minecraft:mace":4,"minecraft:magenta_shulker_box":4,"minecraft:netherite_leggings":2,"minecraft:purple_shulker_box":2,"minecraft:cyan_shulker_box":2,"minecraft:netherite_helmet":2,"minecraft:blue_shulker_box":2,"minecraft:elytra":5,"minecraft:green_shulker_box":5,"minecraft:netherite_sword":2}},"DataVersion":4556}